gc_google_services_api/__init__.py
gc_google_services_api/auth/__init__.py
gc_google_services_api/auth/__tests__/__init__.py
gc_google_services_api/auth/__tests__/test_auth.py
gc_google_services_api/bigquery/__init__.py
gc_google_services_api/bigquery/__tests__/__init__.py
gc_google_services_api/bigquery/__tests__/test_bigquery.py
gc_google_services_api/calendar_api/__init__.py
gc_google_services_api/calendar_api/__tests__/__init__.py
gc_google_services_api/calendar_api/__tests__/test_calendar.py
gc_google_services_api/drive/__init__.py
gc_google_services_api/drive/__tests__/__init__.py
gc_google_services_api/drive/__tests__/test_copy_drive_folder_contents.py
gc_google_services_api/drive/__tests__/test_drive.py
gc_google_services_api/gmail/__init__.py
gc_google_services_api/gmail/__tests__/__init__.py
gc_google_services_api/gmail/__tests__/test_gmail.py
gc_google_services_api/gsheet/__init__.py
gc_google_services_api/gsheet/__tests__/__init__.py
gc_google_services_api/gsheet/__tests__/test_gsheet.py
gc_google_services_api/permissions/__init__.py
gc_google_services_api/permissions/drive.py
gc_google_services_api/permissions/workspace.py
gc_google_services_api/pubsub/__init__.py
gc_google_services_api/pubsub/__tests__/__init__.py
gc_google_services_api/pubsub/__tests__/test_pubsub.py
gc_google_services_api/workspace/__init__.py
gc_google_services_api/workspace/__tests__/__init__.py
gc_google_services_api/workspace/__tests__/test_workspace.py
gc_google_services_api/workspace/__tests__/test_workspacesettings.py
gc_google_services_api/workspace/settings.py
gc_google_services_api-2.4.2.dist-info/METADATA
gc_google_services_api-2.4.2.dist-info/WHEEL
gc_google_services_api-2.4.2.dist-info/licenses/LICENSE
gc_google_services_api-2.4.2.dist-info/RECORD
