Metadata-Version: 2.4
Name: gc-google-services-api
Version: 2.4.2
Summary: Collection of libraries to connect with Google APIs.
License-File: LICENSE
Author: Jonathan Rodríguez Alejos
Author-email: jrodriguez.5716@gmail.com
Requires-Python: >=3.8.1,<4.0.0
Classifier: Programming Language :: Python :: 3
Classifier: Programming Language :: Python :: 3.9
Classifier: Programming Language :: Python :: 3.10
Classifier: Programming Language :: Python :: 3.11
Classifier: Programming Language :: Python :: 3.12
Classifier: Programming Language :: Python :: 3.13
Classifier: Programming Language :: Python :: 3.14
Requires-Dist: google-api-python-client (>=2.80.0,<3.0.0)
Requires-Dist: google-cloud-bigquery (>=3.6.0,<4.0.0)
Requires-Dist: google-cloud-pubsub (>=2.34.0,<3.0.0)
